dunamai/__init__.py
dunamai/__main__.py
dunamai/py.typed
dunamai-1.24.0.dist-info/entry_points.txt
dunamai-1.24.0.dist-info/LICENSE
dunamai-1.24.0.dist-info/METADATA
dunamai-1.24.0.dist-info/WHEEL
dunamai-1.24.0.dist-info/RECORD
