Metadata-Version: 2.1
Name: dunamai
Version: 1.24.0
Summary: Dynamic version generation
Home-page: https://github.com/mtkennerly/dunamai
License: MIT
Keywords: version,versioning,dynamic
Author: Matthew T. Kennerly
Author-email: mtkennerly@gmail.com
Requires-Python: >=3.5
Classifier: Development Status :: 5 - Production/Stable
Classifier: Intended Audience :: End Users/Desktop
Classifier: License :: OSI Approved :: MIT License
Classifier: Natural Language :: English
Classifier: Programming Language :: Python
Classifier: Programming Language :: Python :: 3
Classifier: Programming Language :: Python :: 3.5
Classifier: Programming Language :: Python :: 3.6
Classifier: Programming Language :: Python :: 3.7
Classifier: Programming Language :: Python :: 3.8
Classifier: Programming Language :: Python :: 3.9
Classifier: Programming Language :: Python :: 3.10
Classifier: Programming Language :: Python :: 3.11
Classifier: Programming Language :: Python :: 3.12
Classifier: Programming Language :: Python :: 3.13
Requires-Dist: importlib-metadata (>=1.6.0) ; python_version < "3.8"
Requires-Dist: packaging (>=20.9)
Project-URL: Repository, https://github.com/mtkennerly/dunamai
